<innermodel>
	<transform id="world" tx="0" ty="0" tz="0"  rx="0" ry="0" rz="0">
		<transform id="base" tx="0" ty="127.5" tz="0"  rx="0" ry="0" rz="0">
			<mesh id="baseLearnBot" file="/home/robocomp/robocomp/components/learnbot/learnbot_desings/Learnbot2.1/Learnbot2.1.stl" scale="10,10,10" tx="0" ty="0" tz="0" rx="0.1030000001" ry="0" rz="-0.05000000075" collide="0" />
			<transform id="display" tx="-95" ty="-40" tz="97.5"  rx="-0.009999999776" ry="-0.2256000042" rz="1.340000033">
				<plane id="pantalla" nx="1" size="75,1,51" repeat="1" texture="#000000" />
			</transform>
			<transform id="laser1" tx="-49.5" ty="-97" tz="182"  rx="0" ry="4.679999828" rz="0">
				<!-- <plane id="axis2y" texture="#00ff00" size="2,200,2" repeat="1" nx="1" ny="0" nz="0" px="0" py="100" pz="0" collide="0" /> -->
				<plane id="axis2x" texture="#ff0000" size="2,2,200" repeat="1" nx="1" ny="0" nz="0" px="100" py="0" pz="0" collide="0" />
				<!-- <plane id="axis2z" texture="#0000ff" size="200,2,2" repeat="1" nx="1" ny="0" nz="0" px="0" py="0" pz="100" collide="0" /> -->
			</transform>
			<transform id="laser2" tx="-84.5" ty="-97" tz="167"  rx="0" ry="4.010000229" rz="0">
				<!-- <plane id="axis3y" texture="#00ff00" size="2,200,2" repeat="1" nx="1" ny="0" nz="0" px="0" py="100" pz="0" collide="0" /> -->
				<plane id="axis3x" texture="#ff0000" size="2,2,200" repeat="1" nx="1" ny="0" nz="0" px="100" py="0" pz="0" collide="0" />
				<!-- <plane id="axis3z" texture="#0000ff" size="200,2,2" repeat="1" nx="1" ny="0" nz="0" px="0" py="0" pz="100" collide="0" /> -->
			</transform>
			<transform id="laser3" tx="-105" ty="-97" tz="135.5"  rx="0" ry="3.289999962" rz="0">
				<!-- <plane id="axis4y" texture="#00ff00" size="2,200,2" repeat="1" nx="1" ny="0" nz="0" px="0" py="100" pz="0" collide="0" /> -->
				<plane id="axis4x" texture="#ff0000" size="2,2,200" repeat="1" nx="1" ny="0" nz="0" px="100" py="0" pz="0" collide="0" />
				<!-- <plane id="axis4z" texture="#0000ff" size="200,2,2" repeat="1" nx="1" ny="0" nz="0" px="0" py="0" pz="100" collide="0" /> -->
			</transform>
			<transform id="laser4" tx="-105" ty="-97" tz="96"  rx="0" ry="2.880000114" rz="0">
				<!-- <plane id="axis5y" texture="#00ff00" size="2,200,2" repeat="1" nx="1" ny="0" nz="0" px="0" py="100" pz="0" collide="0" /> -->
				<plane id="axis5x" texture="#ff0000" size="2,2,200" repeat="1" nx="1" ny="0" nz="0" px="100" py="0" pz="0" collide="0" />
				<!-- <plane id="axis5z" texture="#0000ff" size="200,2,2" repeat="1" nx="1" ny="0" nz="0" px="0" py="0" pz="100" collide="0" /> -->
			</transform>
			<transform id="laser5" tx="-90" ty="-97" tz="58"  rx="0" ry="2.420000076" rz="0">
				<!-- <plane id="axis6y" texture="#00ff00" size="2,200,2" repeat="1" nx="1" ny="0" nz="0" px="0" py="100" pz="0" collide="0" /> -->
				<plane id="axis6x" texture="#ff0000" size="2,2,200" repeat="1" nx="1" ny="0" nz="0" px="100" py="0" pz="0" collide="0" />
				<!-- <plane id="axis6z" texture="#0000ff" size="200,2,2" repeat="1" nx="1" ny="0" nz="0" px="0" py="0" pz="100" collide="0" /> -->
			</transform>
			<transform id="laser6" tx="-56.75" ty="-97" tz="38"  rx="0" ry="1.669999957" rz="0">
				<!-- <plane id="axis7y" texture="#00ff00" size="2,200,2" repeat="1" nx="1" ny="0" nz="0" px="0" py="100" pz="0" collide="0" /> -->
				<plane id="axis7x" texture="#ff0000" size="2,2,200" repeat="1" nx="1" ny="0" nz="0" px="100" py="0" pz="0" collide="0" />
				<!-- <plane id="axis7z" texture="#0000ff" size="200,2,2" repeat="1" nx="1" ny="0" nz="0" px="0" py="0" pz="100" collide="0" /> -->
			</transform>
			<transform id="laser7" tx="-18" ty="-97" tz="45"  rx="0" ry="1.139999986" rz="0">
				<!-- <plane id="axis8y" texture="#00ff00" size="2,200,2" repeat="1" nx="1" ny="0" nz="0" px="0" py="100" pz="0" collide="0" /> -->
				<plane id="axis8x" texture="#ff0000" size="2,2,200" repeat="1" nx="1" ny="0" nz="0" px="100" py="0" pz="0" collide="0" />
				<!-- <plane id="axis8z" texture="#0000ff" size="200,2,2" repeat="1" nx="1" ny="0" nz="0" px="0" py="0" pz="100" collide="0" /> -->
			</transform>
			<transform id="view" tx="-200" ty="-12" tz="72"  rx="0" ry="-0.2700000107" rz="-0.3000000119">
				<plane id="axis9y" texture="#00ff00" size="2,200,2" repeat="1" nx="1" ny="0" nz="0" px="0" py="100" pz="0" collide="0" />
				<plane id="axis9x" texture="#ff0000" size="2,2,200" repeat="1" nx="1" ny="0" nz="0" px="100" py="0" pz="0" collide="0" />
				<plane id="axis9z" texture="#0000ff" size="200,2,2" repeat="1" nx="1" ny="0" nz="0" px="0" py="0" pz="100" collide="0" />
				<!-- <rgbd id="viewDisplay" width="320" height="240" focal="480" port="10100" ifconfig="40000,10004" noise="0" /> -->
			</transform>
			<transform id="camera" tx="-86" ty="-3" tz="96"  rx="0" ry="2.880000114" rz="0">
				<joint id="servo" port="20000" axis="x" home="0.6000000238" min="-1.570796371" max="1.570796371" tx="0" ty="0" tz="0"  rx="0" ry="0" rz="0">
    				<plane id="axis10y" texture="#00ff00" size="2,200,2" repeat="1" nx="1" ny="0" nz="0" px="0" py="100" pz="0" collide="0" />
    				<plane id="axis10x" texture="#ff0000" size="2,2,200" repeat="1" nx="1" ny="0" nz="0" px="100" py="0" pz="0" collide="0" />
    				<plane id="axis10z" texture="#0000ff" size="200,2,2" repeat="1" nx="1" ny="0" nz="0" px="0" py="0" pz="100" collide="0" />
					<!-- <rgbd id="rgbdLearnBot" width="320" height="240" focal="480" port="10097" ifconfig="40000,10004" noise="0" /> -->
				</joint>
			</transform>
		</transform>
		<plane id="ddG" texture="/home/robocomp/robocomp/components/learnbot/learnbot_simulator/textures/lines.jpg" size="5000,5000,10" repeat="1000" nx="0" ny="1" nz="0" px="200" py="0" pz="0" collide="0" />
	</transform>
</innermodel>
